odoo/addons/connector_jira_tempo_project_role/README.rst
odoo/addons/connector_jira_tempo_project_role/__init__.py
odoo/addons/connector_jira_tempo_project_role/__manifest__.py
odoo/addons/connector_jira_tempo_project_role/controllers/__init__.py
odoo/addons/connector_jira_tempo_project_role/controllers/project_assignment_tempo.py
odoo/addons/connector_jira_tempo_project_role/i18n/connector_jira_tempo_project_role.pot
odoo/addons/connector_jira_tempo_project_role/models/__init__.py
odoo/addons/connector_jira_tempo_project_role/models/account_analytic_line/__init__.py
odoo/addons/connector_jira_tempo_project_role/models/account_analytic_line/common.py
odoo/addons/connector_jira_tempo_project_role/models/account_analytic_line/importer.py
odoo/addons/connector_jira_tempo_project_role/models/jira_backend/__init__.py
odoo/addons/connector_jira_tempo_project_role/models/jira_backend/common.py
odoo/addons/connector_jira_tempo_project_role/readme/CONFIGURE.rst
odoo/addons/connector_jira_tempo_project_role/readme/CONTRIBUTORS.rst
odoo/addons/connector_jira_tempo_project_role/readme/DESCRIPTION.rst
odoo/addons/connector_jira_tempo_project_role/static/description/icon.png
odoo/addons/connector_jira_tempo_project_role/static/description/index.html
odoo/addons/connector_jira_tempo_project_role/tests/__init__.py
odoo/addons/connector_jira_tempo_project_role/tests/common.py
odoo/addons/connector_jira_tempo_project_role/tests/test_connector_jira_tempo_project_role.py
odoo/addons/connector_jira_tempo_project_role/tests/fixtures/cassettes/test_import_worklog_project_role.yaml
odoo/addons/connector_jira_tempo_project_role/tests/fixtures/cassettes/test_import_worklog_project_role_missing.yaml
odoo/addons/connector_jira_tempo_project_role/tests/fixtures/cassettes/test_import_worklog_project_role_not_set.yaml
odoo/addons/connector_jira_tempo_project_role/views/jira_backend.xml
odoo12_addon_connector_jira_tempo_project_role-12.0.1.1.0.dist-info/METADATA
odoo12_addon_connector_jira_tempo_project_role-12.0.1.1.0.dist-info/WHEEL
odoo12_addon_connector_jira_tempo_project_role-12.0.1.1.0.dist-info/top_level.txt
odoo12_addon_connector_jira_tempo_project_role-12.0.1.1.0.dist-info/RECORD
