Metadata-Version: 2.1
Name: odoo12-addon-connector-jira-tempo-project-role
Version: 12.0.1.1.0
Summary: Provide Assigments to Tempo and import Roles from Worklogs
Home-page: https://github.com/OCA/connector-jira
Author: Brainbean Apps, Odoo Community Association (OCA)
Author-email: support@odoo-community.org
License: AGPL-3
Platform: UNKNOWN
Classifier: Programming Language :: Python
Classifier: Framework :: Odoo
Classifier: License :: OSI Approved :: GNU Affero General Public License v3
Requires-Python: >=3.5
Requires-Dist: odoo12-addon-connector-jira-tempo-base
Requires-Dist: odoo12-addon-hr-timesheet-role
Requires-Dist: odoo12-addon-project-role
Requires-Dist: odoo (<12.1dev,>=12.0a)
